[
    {
        "id": "mos1",
        "colour": "#d41317",
        "fg": "#fff",
        "name": {
            "en": "Line 1",
            "zh-Hans": "1号线",
            "zh-Hant": "1號綫",
            "ru": "Сокольническая"
        }
    },
    {
        "id": "mos2",
        "colour": "#4baf51",
        "fg": "#fff",
        "name": {
            "en": "Line 2",
            "zh-Hans": "2号线",
            "zh-Hant": "2號綫",
            "ru": "Замоскворецкая"
        }
    },
    {
        "id": "mos3",
        "colour": "#0072ba",
        "fg": "#fff",
        "name": {
            "en": "Line 3",
            "zh-Hans": "3号线",
            "zh-Hant": "3號綫",
            "ru": "Арбатско-Покровская"
        }
    },
    {
        "id": "mos4",
        "colour": "#1ebcef",
        "fg": "#fff",
        "name": {
            "en": "Line 4",
            "zh-Hans": "4号线",
            "zh-Hant": "4號綫",
            "ru": "Филёвская"
        }
    },
    {
        "id": "mos5",
        "colour": "#905134",
        "fg": "#fff",
        "name": {
            "en": "Line 5",
            "zh-Hans": "5号线",
            "zh-Hant": "5號綫",
            "ru": "Кольцевая"
        }
    },
    {
        "id": "mos6",
        "colour": "#ef7d00",
        "fg": "#fff",
        "name": {
            "en": "Line 6",
            "zh-Hans": "6号线",
            "zh-Hant": "6號綫",
            "ru": "Калужско-Рижская"
        }
    },
    {
        "id": "mos7",
        "colour": "#933f8f",
        "fg": "#fff",
        "name": {
            "en": "Line 7",
            "zh-Hans": "7号线",
            "zh-Hant": "7號綫",
            "ru": "Таганско-Краснопресненская"
        }
    },
    {
        "id": "mos8",
        "colour": "#ffdd00",
        "fg": "#fff",
        "name": {
            "en": "Line 8",
            "zh-Hans": "8号线",
            "zh-Hant": "8號綫",
            "ru": "Калининская"
        }
    },
    {
        "id": "mos9",
        "colour": "#adabac",
        "fg": "#fff",
        "name": {
            "en": "Line 9",
            "zh-Hans": "9号线",
            "zh-Hant": "9號綫",
            "ru": "Серпуховско-Тимирязевская"
        }
    },
    {
        "id": "mos10",
        "colour": "#b4cc04",
        "fg": "#fff",
        "name": {
            "en": "Line 10",
            "zh-Hans": "10号线",
            "zh-Hant": "10號綫",
            "ru": "Люблинско-Дмитровская"
        }
    },
    {
        "id": "mos11",
        "colour": "#88cdcf",
        "fg": "#fff",
        "name": {
            "en": "Line 11",
            "zh-Hans": "11号线",
            "zh-Hant": "11號綫",
            "ru": "Каховская"
        }
    },
    {
        "id": "mos12",
        "colour": "#bac8e8",
        "fg": "#fff",
        "name": {
            "en": "Line 12",
            "zh-Hans": "12号线",
            "zh-Hant": "12號綫",
            "ru": "Бутовская"
        }
    },
    {
        "id": "mos13",
        "colour": "#0273ba",
        "fg": "#fff",
        "name": {
            "en": "Line 13",
            "zh-Hans": "13号线",
            "zh-Hant": "13號綫",
            "ru": "Московский монорельс"
        }
    },
    {
        "id": "mos14",
        "colour": "#d5191d",
        "fg": "#fff",
        "name": {
            "en": "Line 14",
            "zh-Hans": "14号线",
            "zh-Hant": "14號綫",
            "ru": "Московское Центральное Кольцо"
        }
    },
    {
        "id": "mos15",
        "colour": "#ed7cae",
        "fg": "#fff",
        "name": {
            "en": "Line 15",
            "zh-Hans": "15号线",
            "zh-Hant": "15號綫",
            "ru": "Некрасовская"
        }
    },
    {
        "id": "mosd1",
        "colour": "#f7a600",
        "fg": "#fff",
        "name": {
            "en": "D1",
            "zh-Hans": "D1 白俄罗斯-萨维奥洛沃直径线",
            "zh-Hant": "D1 白俄羅斯-薩維奧洛沃直徑綫",
            "ru": "Белорусско-Савёловский диаметр"
        }
    },
    {
        "id": "mosd2",
        "colour": "#e94282",
        "fg": "#fff",
        "name": {
            "en": "D2",
            "zh-Hans": "D2 库尔斯克-里加直径线",
            "zh-Hant": "D2 庫爾斯克-里加直徑綫",
            "ru": "Курско-Рижский диаметр"
        }
    },
    {
        "id": "mosd3",
        "colour": "#e95c0e",
        "fg": "#fff",
        "name": {
            "en": "D3",
            "zh-Hans": "D3 列宁格勒-喀山直径线",
            "zh-Hant": "D3 列寧格勒-喀山直徑綫",
            "ru": "Ленинградско-Казанский диаметр"
        }
    },
    {
        "id": "mosd4",
        "colour": "#4db488",
        "fg": "#fff",
        "name": {
            "en": "D4",
            "zh-Hans": "D4 基辅-高尔基直径线",
            "zh-Hant": "D4 基輔-高爾基直徑綫",
            "ru": "Киевско-Горьковский диаметр"
        }
    }
]
