[
    {
        "id": "xm1",
        "colour": "#E27326",
        "fg": "#fff",
        "name": {
            "en": "Line 1",
            "zh-Hans": "1号线",
            "zh-Hant": "1號線"
        }
    },
    {
        "id": "xm2",
        "colour": "#52AB43",
        "fg": "#fff",
        "name": {
            "en": "Line 2",
            "zh-Hans": "2号线",
            "zh-Hant": "2號線"
        }
    },
    {
        "id": "xm3",
        "colour": "#2EC6D6",
        "fg": "#fff",
        "name": {
            "en": "Line 3",
            "zh-Hans": "3号线",
            "zh-Hant": "3號線"
        }
    },
    {
        "id": "xmb",
        "colour": "#00A5A6",
        "fg": "#fff",
        "name": {
            "en": "BRT",
            "zh-Hans": "快速公交",
            "zh-Hant": "快速公交"
        }
    },
    {
        "id": "xm4",
        "colour": "#FF0000",
        "fg": "#fff",
        "name": {
            "en": "Line 4",
            "zh-Hans": "4号线",
            "zh-Hant": "4号線"
        }
    },
    {
        "id": "xm6",
        "colour": "#C70789",
        "fg": "#fff",
        "name": {
            "en": "Line 6",
            "zh-Hans": "6号线",
            "zh-Hant": "6号線"
        }
    }
]
